README.md
setup.py
mrldb/__init__.py
mrldb/db_types.py
mrldb/dbutils.py
mrldb/errors.py
mrldb/mrl_cluster.py
mrldb/struct.py
mrldb/type_aiomysql.py
mrldb/type_cassandra.py
mrldb/type_mysql.py
mrldb/type_sqlite.py
mrldb.egg-info/PKG-INFO
mrldb.egg-info/SOURCES.txt
mrldb.egg-info/dependency_links.txt
mrldb.egg-info/top_level.txt
mrldb_old/__init__.py
mrldb_old/db_types.py
mrldb_old/dbutils.py
mrldb_old/errors.py
mrldb_old/mrl_cluster.py
mrldb_old/struct.py
mrldb_old/type_aiomysql.py
mrldb_old/type_cassandra.py
mrldb_old/type_mysql.py
mrldb_old/type_sqlite.py