Metadata-Version: 2.1
Name: mrldb
Version: 0.1.4
Summary: A library to handle your databases: cassandra, mariadb, (mysql), sqlite3
Home-page: https://github.com/merlleu/mrldb
Author: Rémi 'Mr e-RL'LANGDORPH
Author-email: r.langdorph@gmail.com
License: UNKNOWN
Platform: UNKNOWN
Classifier: Programming Language :: Python :: 3
Classifier: License :: OSI Approved :: MIT License
Classifier: Operating System :: OS Independent
